ARS_Test_Runner/__init__.py
ARS_Test_Runner/cli.py
ARS_Test_Runner/semantic_test.py
ARS_Test_Runner/templates/affects_creative.json
ARS_Test_Runner/templates/treats.json
ARS_Test_Runner/templates/treats_creative.json
ARS_Test_Runner-0.2.6.dist-info/METADATA
ARS_Test_Runner-0.2.6.dist-info/WHEEL
ARS_Test_Runner-0.2.6.dist-info/entry_points.txt
ARS_Test_Runner-0.2.6.dist-info/top_level.txt
ARS_Test_Runner-0.2.6.dist-info/RECORD
