Metadata-Version: 2.1
Name: ARS-Test-Runner
Version: 0.2.6
Summary: Python package for ARS pass/fail test
Home-page: https://github.com/NCATSTranslator/ARS_Test_Runner
Author: Shervin Abdollahi, Mark Williams
Author-email: shervin.abdollahi@Nih.gov, mark.williams5@nih.gov
License: Public Domain
Classifier: Development Status :: 2 - Pre-Alpha
Classifier: Natural Language :: English
Classifier: Programming Language :: Python :: 3
Requires-Dist: attrs >=20.3.0
Requires-Dist: click
Requires-Dist: httpx
Requires-Dist: numpy
Requires-Dist: reasoner-validator
Requires-Dist: requests
Requires-Dist: twine
